somerandom/__init__.py
somerandom/api_helper.py
somerandom/configuration.py
somerandom/decorators.py
somerandom/somerandom_client.py
somerandom/controllers/__init__.py
somerandom/controllers/base_controller.py
somerandom/controllers/estimates_controller.py
somerandom/controllers/products_controller.py
somerandom/controllers/user_controller.py
somerandom/exceptions/__init__.py
somerandom/exceptions/api_exception.py
somerandom/exceptions/error_exception.py
somerandom/http/__init__.py
somerandom/http/http_call_back.py
somerandom/http/http_client.py
somerandom/http/http_context.py
somerandom/http/http_method_enum.py
somerandom/http/http_request.py
somerandom/http/http_response.py
somerandom/http/requests_client.py
somerandom/http/auth/__init__.py
somerandom/http/auth/custom_query_auth.py
somerandom/models/__init__.py
somerandom/models/activities.py
somerandom/models/activity.py
somerandom/models/price_estimate.py
somerandom/models/product.py
somerandom/models/product_list.py
somerandom/models/profile.py
somerandom-5.1.dist-info/LICENSE
somerandom-5.1.dist-info/METADATA
somerandom-5.1.dist-info/WHEEL
somerandom-5.1.dist-info/top_level.txt
somerandom-5.1.dist-info/RECORD
